{"type": "FeatureCollection", "features": [{"bbox": [9.1, 45.52, 9.11, 45.53], "geometry": {"coordinates": [[[9.1, 45.52], [9.11, 45.52], [9.11, 45.53], [9.1, 45.53], [9.1, 45.52]]], "type": "Polygon"}, "properties": {"name": "C20021Z01 0:0", "cap": "CAP-20021", "zona": "ZONA-01", "square": 0, "cap_zona_square": "CAP-20021_ZONA-01_0"}, "type": "Feature"}, {"bbox": [9.11, 45.52, 9.12, 45.53], "geometry": {"coordinates": [[[9.11, 45.52], [9.12, 45.52], [9.12, 45.53], [9.11, 45.53], [9.11, 45.52]]], "type": "Polygon"}, "properties": {"name": "C20021Z01 1:0", "cap": "CAP-20021", "zona": "ZONA-01", "square": 1, "cap_zona_square": "CAP-20021_ZONA-01_1"}, "type": "Feature"}, {"bbox": [9.11, 45.53, 9.12, 45.54], "geometry": {"coordinates": [[[9.11, 45.53], [9.12, 45.53], [9.12, 45.54], [9.11, 45.54], [9.11, 45.53]]], "type": "Polygon"}, "properties": {"name": "C20021Z01 1:1", "cap": "CAP-20021", "zona": "ZONA-01", "square": 2, "cap_zona_square": "CAP-20021_ZONA-01_2"}, "type": "Feature"}, {"bbox": [9.09, 45.53, 9.1, 45.54], "geometry": {"coordinates": [[[9.09, 45.53], [9.1, 45.53], [9.1, 45.54], [9.09, 45.54], [9.09, 45.53]]], "type": "Polygon"}, "properties": {"name": "C20021Z02 1:0", "cap": "CAP-20021", "zona": "ZONA-02", "square": 0, "cap_zona_square": "CAP-20021_ZONA-02_0"}, "type": "Feature"}, {"bbox": [9.1, 45.53, 9.11, 45.54], "geometry": {"coordinates": [[[9.1, 45.53], [9.11, 45.53], [9.11, 45.54], [9.1, 45.54], [9.1, 45.53]]], "type": "Polygon"}, "properties": {"name": "C20021Z02 2:0", "cap": "CAP-20021", "zona": "ZONA-02", "square": 1, "cap_zona_square": "CAP-20021_ZONA-02_1"}, "type": "Feature"}, {"bbox": [9.09, 45.54, 9.1, 45.55], "geometry": {"coordinates": [[[9.09, 45.54], [9.1, 45.54], [9.1, 45.55], [9.09, 45.55], [9.09, 45.54]]], "type": "Polygon"}, "properties": {"name": "C20021Z02 1:1", "cap": "CAP-20021", "zona": "ZONA-02", "square": 2, "cap_zona_square": "CAP-20021_ZONA-02_2"}, "type": "Feature"}, {"bbox": [9.1, 45.54, 9.11, 45.55], "geometry": {"coordinates": [[[9.1, 45.54], [9.11, 45.54], [9.11, 45.55], [9.1, 45.55], [9.1, 45.54]]], "type": "Polygon"}, "properties": {"name": "C20021Z02 2:1", "cap": "CAP-20021", "zona": "ZONA-02", "square": 3, "cap_zona_square": "CAP-20021_ZONA-02_3"}, "type": "Feature"}, {"bbox": [9.11, 45.54, 9.12, 45.55], "geometry": {"coordinates": [[[9.11, 45.54], [9.12, 45.54], [9.12, 45.55], [9.11, 45.55], [9.11, 45.54]]], "type": "Polygon"}, "properties": {"name": "C20021Z02 3:1", "cap": "CAP-20021", "zona": "ZONA-02", "square": 4, "cap_zona_square": "CAP-20021_ZONA-02_4"}, "type": "Feature"}, {"bbox": [9.12, 45.54, 9.129999999999999, 45.55], "geometry": {"coordinates": [[[9.12, 45.54], [9.129999999999999, 45.54], [9.129999999999999, 45.55], [9.12, 45.55], [9.12, 45.54]]], "type": "Polygon"}, "properties": {"name": "C20021Z02 4:1", "cap": "CAP-20021", "zona": "ZONA-02", "square": 5, "cap_zona_square": "CAP-20021_ZONA-02_5"}, "type": "Feature"}, {"bbox": [9.129999999999999, 45.54, 9.139999999999999, 45.55], "geometry": {"coordinates": [[[9.129999999999999, 45.54], [9.139999999999999, 45.54], [9.139999999999999, 45.55], [9.129999999999999, 45.55], [9.129999999999999, 45.54]]], "type": "Polygon"}, "properties": {"name": "C20021Z02 5:1", "cap": "CAP-20021", "zona": "ZONA-02", "square": 6, "cap_zona_square": "CAP-20021_ZONA-02_6"}, "type": "Feature"}, {"bbox": [9.09, 45.55, 9.1, 45.559999999999995], "geometry": {"coordinates": [[[9.09, 45.55], [9.1, 45.55], [9.1, 45.559999999999995], [9.09, 45.559999999999995], [9.09, 45.55]]], "type": "Polygon"}, "properties": {"name": "C20021Z02 1:2", "cap": "CAP-20021", "zona": "ZONA-02", "square": 7, "cap_zona_square": "CAP-20021_ZONA-02_7"}, "type": "Feature"}, {"bbox": [9.1, 45.55, 9.11, 45.559999999999995], "geometry": {"coordinates": [[[9.1, 45.55], [9.11, 45.55], [9.11, 45.559999999999995], [9.1, 45.559999999999995], [9.1, 45.55]]], "type": "Polygon"}, "properties": {"name": "C20021Z02 2:2", "cap": "CAP-20021", "zona": "ZONA-02", "square": 8, "cap_zona_square": "CAP-20021_ZONA-02_8"}, "type": "Feature"}, {"bbox": [9.11, 45.55, 9.12, 45.559999999999995], "geometry": {"coordinates": [[[9.11, 45.55], [9.12, 45.55], [9.12, 45.559999999999995], [9.11, 45.559999999999995], [9.11, 45.55]]], "type": "Polygon"}, "properties": {"name": "C20021Z02 3:2", "cap": "CAP-20021", "zona": "ZONA-02", "square": 9, "cap_zona_square": "CAP-20021_ZONA-02_9"}, "type": "Feature"}, {"bbox": [9.12, 45.55, 9.129999999999999, 45.559999999999995], "geometry": {"coordinates": [[[9.12, 45.55], [9.129999999999999, 45.55], [9.129999999999999, 45.559999999999995], [9.12, 45.559999999999995], [9.12, 45.55]]], "type": "Polygon"}, "properties": {"name": "C20021Z02 4:2", "cap": "CAP-20021", "zona": "ZONA-02", "square": 10, "cap_zona_square": "CAP-20021_ZONA-02_10"}, "type": "Feature"}, {"bbox": [9.129999999999999, 45.55, 9.139999999999999, 45.559999999999995], "geometry": {"coordinates": [[[9.129999999999999, 45.55], [9.139999999999999, 45.55], [9.139999999999999, 45.559999999999995], [9.129999999999999, 45.559999999999995], [9.129999999999999, 45.55]]], "type": "Polygon"}, "properties": {"name": "C20021Z02 5:2", "cap": "CAP-20021", "zona": "ZONA-02", "square": 11, "cap_zona_square": "CAP-20021_ZONA-02_11"}, "type": "Feature"}, {"bbox": [9.139999999999999, 45.55, 9.149999999999999, 45.559999999999995], "geometry": {"coordinates": [[[9.139999999999999, 45.55], [9.149999999999999, 45.55], [9.149999999999999, 45.559999999999995], [9.139999999999999, 45.559999999999995], [9.139999999999999, 45.55]]], "type": "Polygon"}, "properties": {"name": "C20021Z02 6:2", "cap": "CAP-20021", "zona": "ZONA-02", "square": 12, "cap_zona_square": "CAP-20021_ZONA-02_12"}, "type": "Feature"}, {"bbox": [9.09, 45.559999999999995, 9.1, 45.56999999999999], "geometry": {"coordinates": [[[9.09, 45.559999999999995], [9.1, 45.559999999999995], [9.1, 45.56999999999999], [9.09, 45.56999999999999], [9.09, 45.559999999999995]]], "type": "Polygon"}, "properties": {"name": "C20021Z02 1:3", "cap": "CAP-20021", "zona": "ZONA-02", "square": 13, "cap_zona_square": "CAP-20021_ZONA-02_13"}, "type": "Feature"}, {"bbox": [9.1, 45.559999999999995, 9.11, 45.56999999999999], "geometry": {"coordinates": [[[9.1, 45.559999999999995], [9.11, 45.559999999999995], [9.11, 45.56999999999999], [9.1, 45.56999999999999], [9.1, 45.559999999999995]]], "type": "Polygon"}, "properties": {"name": "C20021Z02 2:3", "cap": "CAP-20021", "zona": "ZONA-02", "square": 14, "cap_zona_square": "CAP-20021_ZONA-02_14"}, "type": "Feature"}, {"bbox": [9.139999999999999, 45.559999999999995, 9.149999999999999, 45.56999999999999], "geometry": {"coordinates": [[[9.139999999999999, 45.559999999999995], [9.149999999999999, 45.559999999999995], [9.149999999999999, 45.56999999999999], [9.139999999999999, 45.56999999999999], [9.139999999999999, 45.559999999999995]]], "type": "Polygon"}, "properties": {"name": "C20021Z02 6:3", "cap": "CAP-20021", "zona": "ZONA-02", "square": 15, "cap_zona_square": "CAP-20021_ZONA-02_15"}, "type": "Feature"}]}